Metadata-Version: 2.1
Name: lagoons-distributions
Version: 0.1
Summary: Probability distributions
Author: Harris Ramos Baroni
Author-email: yuopres@gmail.com
